bel_enrichment/__init__.py
bel_enrichment/__main__.py
bel_enrichment/cli.py
bel_enrichment/indra_utils.py
bel_enrichment/ranking.py
bel_enrichment/repository.py
bel_enrichment/sheets.py
bel_enrichment/summary.py
bel_enrichment/workflow.py
bel_enrichment-0.0.5.dist-info/LICENSE
bel_enrichment-0.0.5.dist-info/METADATA
bel_enrichment-0.0.5.dist-info/WHEEL
bel_enrichment-0.0.5.dist-info/entry_points.txt
bel_enrichment-0.0.5.dist-info/top_level.txt
bel_enrichment-0.0.5.dist-info/RECORD
