Metadata-Version: 2.1
Name: bel-enrichment
Version: 0.0.5
Summary: A package for generating curation sheets for rationally enriching a BEL graph using INDRA and PyBEL.
Home-page: https://github.com/bel-enrichment/bel-enrichment
Author: Charles Tapley Hoyt
Author-email: cthoyt@gmail.com
Maintainer: Charles Tapley Hoyt
Maintainer-email: cthoyt@gmail.com
License: MIT
Download-URL: https://github.com/bel-enrichment/bel-enrichment/releases
Project-URL: Bug Tracker, https://github.com/bel-enrichment/bel-enrichment/issues
Project-URL: Source Code, https://github.com/bel-enrichment/bel-enrichment
Keywords: Biological Expression Language,BEL,Domain Specific Language,DSL,Systems Biology,Networks Biology
Platform: UNKNOWN
Classifier: Development Status :: 4 - Beta
Classifier: Environment :: Console
Classifier: Intended Audience :: Developers
Classifier: Intended Audience :: Science/Research
Classifier: License :: OSI Approved :: MIT License
Classifier: Operating System :: OS Independent
Classifier: Programming Language :: Python
Classifier: Programming Language :: Python :: 3.8
Classifier: Programming Language :: Python :: 3.7
Classifier: Programming Language :: Python :: 3.6
Classifier: Programming Language :: Python :: 3 :: Only
Classifier: Topic :: Scientific/Engineering :: Bio-Informatics
Classifier: Topic :: Scientific/Engineering :: Chemistry
Requires-Python: >=3.6
Requires-Dist: pybel (>=0.14.6)
Requires-Dist: bel-repository
Requires-Dist: indra
Requires-Dist: xlrd
Provides-Extra: docs
Requires-Dist: sphinx ; extra == 'docs'
Requires-Dist: sphinx-rtd-theme ; extra == 'docs'
Requires-Dist: sphinx-click ; extra == 'docs'
